LICENSE
seesv/__init__.py
seesv/delimitedfile.py
seesv-0.1.2.dist-info/LICENSE
seesv-0.1.2.dist-info/WHEEL
seesv-0.1.2.dist-info/METADATA
seesv-0.1.2.dist-info/RECORD
