Metadata-Version: 2.1
Name: seesv
Version: 0.1.2
Summary: A Python library providing fast access to data in very large delimited data files (CSV, TSV, pipe-delimited, etc).
Home-page: https://github.com/davealexis/pyseesv
License: MIT
Keywords: csv,delimited files
Author: David Alexis
Author-email: dalexis@gmail.com
Requires-Python: >=3.9,<4.0
Classifier: License :: OSI Approved :: MIT License
Classifier: Programming Language :: Python :: 3
Classifier: Programming Language :: Python :: 3.9
Project-URL: Repository, https://github.com/davealexis/pyseesv
